README.md
setup.py
COVID19Py/__init__.py
COVID19Py/covid19.py
COVID19Py.egg-info/PKG-INFO
COVID19Py.egg-info/SOURCES.txt
COVID19Py.egg-info/dependency_links.txt
COVID19Py.egg-info/top_level.txt