Metadata-Version: 2.1
Name: COVID19Py
Version: 0.1.0
Summary: Python API Wrapper for tracking Coronavirus (COVID-19, SARS-CoV-2) via https://github.com/ExpDev07/coronavirus-tracker-api
Home-page: https://github.com/Kamaropoulos/covid19py
Author: Konstantinos Kamaropoulos
Author-email: k@kamaropoulos.com
License: UNKNOWN
Keywords: covid19,coronavirus,api
Platform: UNKNOWN
Classifier: Programming Language :: Python :: 2
Classifier: Programming Language :: Python :: 2.7
Classifier: Programming Language :: Python :: 3
Classifier: Programming Language :: Python :: 3.4
Classifier: Programming Language :: Python :: 3.5
Classifier: Programming Language :: Python :: 3.6
Classifier: Programming Language :: Python :: 3.7
Classifier: Programming Language :: Python :: 3.8
Classifier: Operating System :: OS Independent
Requires-Python: >=2.7, !=3.0.*, !=3.1.*, !=3.2.*, !=3.3.*, !=3.4.*
